setup.py
mod_pbxproj/__init__.py
mod_pbxproj/__main__.py
mod_pbxproj/mod_pbxproj.py
mod_pbxproj.egg-info/PKG-INFO
mod_pbxproj.egg-info/SOURCES.txt
mod_pbxproj.egg-info/dependency_links.txt
mod_pbxproj.egg-info/requires.txt
mod_pbxproj.egg-info/top_level.txt