Metadata-Version: 1.0
Name: mod-pbxproj
Version: 1.3
Summary: XCode Project Generator for Python
Home-page: http://github.com/kronenthaler/mod-pbxproj
Author: Ignacio Calderon
Author-email: UNKNOWN
License: BSD License
Platform: UNKNOWN
